{
	"configurations" : 
	[
		{
			"directories" : 
			[
				{
					"build" : ".",
					"jsonFile" : "directory-.-Debug-f5ebdc15457944623624.json",
					"minimumCMakeVersion" : 
					{
						"string" : "3.4.1"
					},
					"projectIndex" : 0,
					"source" : ".",
					"targetIndexes" : 
					[
						0
					]
				}
			],
			"name" : "Debug",
			"projects" : 
			[
				{
					"directoryIndexes" : 
					[
						0
					],
					"name" : "Project",
					"targetIndexes" : 
					[
						0
					]
				}
			],
			"targets" : 
			[
				{
					"directoryIndex" : 0,
					"id" : "native-lib::@6890427a1f51a3e7e1df",
					"jsonFile" : "target-native-lib-Debug-019713253a1d80a8d820.json",
					"name" : "native-lib",
					"projectIndex" : 0
				}
			]
		}
	],
	"kind" : "codemodel",
	"paths" : 
	{
		"build" : "/Users/kaka/Documents/GoogleCamera/Camera2Test/app/.cxx/Debug/6vk1im5o/arm64-v8a",
		"source" : "/Users/kaka/Documents/GoogleCamera/Camera2Test/app"
	},
	"version" : 
	{
		"major" : 2,
		"minor" : 3
	}
}
